{
  "updated": "2026-05-07T00:51:18Z",
  "source": "Public RSS — international outlets (strict filter)",
  "feedsOk": 15,
  "feedsTotal": 15,
  "items": [
    {
      "id": "nik-0292aab7e787",
      "title": "Japan stocks surge to new high amid potential deal to end Iran war",
      "description": "",
      "url": "https://asia.nikkei.com/business/markets/japan-stocks-surge-to-new-high-amid-potential-deal-to-end-iran-war",
      "source": "Nikkei Asia",
      "publishedAt": "2026-05-07T00:51:15Z",
      "image": "https://images.ft.com/v3/image/raw/https%3A%2F%2Fcms-image-bucket-productionv3-ap-northeast-1-a7d2.s3.ap-northeast-1.amazonaws.com%2Fimages%2F8%2F7%2F2%2F1%2F12461278-1-eng-GB%2F5a6250985985-photo_SXM2026050700001629.jpg?width=1260&amp;fit=cover&amp;gravity=faces&amp;dpr=2&amp;quality=medium&amp;source=nar-cms&amp;format=auto&amp;height=630",
      "categories": [
        "conflict"
      ],
      "relevanceScore": 3,
      "isAnalysis": false,
      "tags": []
    },
    {
      "id": "al -24f3c14fe93d",
      "title": "Israel bombs Beirut’s southern suburb as it targets Hezbollah commander",
      "description": "It was the first attack on Beirut&#039;s southern suburbs since a truce in the Israel-Hezbollah war went into force on April 17.",
      "url": "https://www.aljazeera.com/news/2026/5/6/israel-bombs-beiruts-southern-suburb-as-it-targets-radwan-force-commander?traffic_source=rss",
      "source": "Al Jazeera",
      "publishedAt": "2026-05-06T17:35:39Z",
      "image": "https://www.aljazeera.com/wp-content/uploads/2026/05/AFP__20260506__B22M8WG__v1__HighRes__LebanonIsraelIranUsWar-1778092574.jpg?resize=1920%2C1440",
      "categories": [
        "conflict"
      ],
      "relevanceScore": 10,
      "isAnalysis": false,
      "tags": []
    },
    {
      "id": "tim-4041dd0a21ae",
      "title": "Iran war possibly motivated Trump dinner shooting suspect, US intel report finds",
      "description": "Initial probe into social media posts finds Cole Allen had 'multiple' grievances, including Iran war, Trump's immigration policies, Elon Musk and Russia's invasion of Ukraine The post Iran war possibly motivated Trump dinner shooting suspect, US intel report finds appeared first on The Times of Israel.",
      "url": "https://www.timesofisrael.com/iran-war-possibly-motivated-trump-dinner-shooting-suspect-us-intel-report-finds/",
      "source": "Times of Israel",
      "publishedAt": "2026-05-06T16:46:55Z",
      "image": "https://static-cdn.toi-media.com/www/uploads/2026/04/686545234-1024x640.jpg",
      "categories": [
        "conflict"
      ],
      "relevanceScore": 7,
      "isAnalysis": false,
      "tags": []
    },
    {
      "id": "kyi-e932c81af3d0",
      "title": "Ceasefire Violations, Nuclear Missile Tests, and Putin’s Coup Rumors – Ukraine Latest, May 6",
      "description": "Zelensky’s response to Russia’s ceasefire violations, Russia’s plan to test nuclear-capable missiles, and potential breakthroughs in US-Iran war – updates from Ukraine and beyond",
      "url": "https://www.kyivpost.com/post/75573",
      "source": "Kyiv Post",
      "publishedAt": "2026-05-06T16:15:00Z",
      "image": "https://static.kyivpost.com/storage/2026/05/06/20a856821e7e1605bec6e1094e7a73c5.jpg?w=640&q=90&f=jpg",
      "categories": [
        "conflict"
      ],
      "relevanceScore": 12,
      "isAnalysis": false,
      "tags": []
    },
    {
      "id": "the-344aa04d75a0",
      "title": "‘Putin only cares about parades’: fury as Russia rains missiles on Ukraine during 24-hour truce",
      "description": "Dozens killed despite ceasefire announced by Zelenskyy, after Moscow asked for Saturday truce for military paradeEurope live – latest updatesKyiv has criticised Russia for attacking several Ukrainian cities overnight with more than 100 combat drones and three missiles in spite of a unilateral 24-hour ceasefire called b…",
      "url": "https://www.theguardian.com/world/2026/may/06/russia-ukraine-missiles-24-hour-ceasefire-military-parade",
      "source": "The Guardian",
      "publishedAt": "2026-05-06T16:01:56Z",
      "image": "https://i.guim.co.uk/img/media/ca67b42bbf7e29547f743466873ee707e0da4e5b/177_0_4735_3790/master/4735.jpg?width=140&quality=85&auto=format&fit=max&s=bc0980c9dac941156a52352437029b81",
      "categories": [
        "conflict"
      ],
      "relevanceScore": 12,
      "isAnalysis": false,
      "tags": []
    },
    {
      "id": "fra-e20be1b0d992",
      "title": "India 'funds organisations behind terror activities in Pakistan': Bilawal Bhutto Zardari",
      "description": "In an interview with FRANCE 24, Bilawal Bhutto Zardari, head of the Pakistan People's Party, discussed the ongoing tensions between India and Pakistan. One year ago, after a five-day war between the two countries, US President Donald Trump announced a full ceasefire, but \"there are underlying tensions that can, at any …",
      "url": "https://www.france24.com/en/tv-shows/t%C3%AAte-%C3%A0-t%C3%AAte/20260506-india-funds-organisations-behind-terror-activities-in-pakistan-bilawal-bhutto-zardari",
      "source": "France24",
      "publishedAt": "2026-05-06T15:32:38Z",
      "image": "https://s.france24.com/media/display/e639777c-4932-11f1-922e-005056a90284/w:1024/p:16x9/TETE-A-TETE-06-05-2026-11-20-ING34-CLEAN-B.png",
      "categories": [
        "conflict"
      ],
      "relevanceScore": 6,
      "isAnalysis": false,
      "tags": []
    },
    {
      "id": "deu-3128d22f0e58",
      "title": "Myanmar: What's behind Suu Kyi's transfer to house arrest?",
      "description": "The transfer of Aung San Suu Kyi from prison to house arrest has been welcomed cautiously abroad, but experts say Myanmar's military may be using it to boost legitimacy as the nation remains engulfed in civil war.",
      "url": "https://www.dw.com/en/myanmar-what-s-behind-suu-kyi-s-transfer-to-house-arrest/a-77066625?maca=en-rss-en-world-4025-rdf",
      "source": "Deutsche Welle",
      "publishedAt": "2026-05-06T14:23:00Z",
      "image": "https://static.dw.com/image/73914367_6.jpg",
      "categories": [
        "conflict"
      ],
      "relevanceScore": 4,
      "isAnalysis": false,
      "tags": []
    },
    {
      "id": "le -419df632e3db",
      "title": "'The Gulf cold war is set to give the other petro-monarchies cold sweats'",
      "description": "The United Arab Emirates' abrupt departure from OPEC on April 28 confirms its determination to break free from Saudi Arabia and is expected to have repercussions across the Middle East, writes columnist Gilles Paris.",
      "url": "https://www.lemonde.fr/en/opinion/article/2026/05/06/the-gulf-cold-war-is-set-to-give-the-other-petro-monarchies-cold-sweats_6753185_23.html",
      "source": "Le Monde (EN)",
      "publishedAt": "2026-05-06T12:22:09Z",
      "image": "https://img.lemde.fr/2026/04/28/517/0/3621/1810/644/322/60/0/f22cc8d_ftp-1-uncv3xg55jjz-2026-04-28t115533z-1897026753-rc2aykamqufh-rtrmadp-3-gulf-summit.JPG",
      "categories": [
        "conflict",
        "analysis"
      ],
      "relevanceScore": 6,
      "isAnalysis": true,
      "tags": []
    },
    {
      "id": "bbc-424f2410ae2d",
      "title": "Robot wars - what an operation in Ukraine tells us about the battlefield of the near future",
      "description": "After Ukraine's President Zelensky said territory had been captured using just robots and drones, what is the future of unmanned warfare?",
      "url": "https://www.bbc.com/news/articles/c9d35v126vyo?at_medium=RSS&at_campaign=rss",
      "source": "BBC",
      "publishedAt": "2026-05-06T11:59:44Z",
      "image": "https://ichef.bbci.co.uk/ace/standard/240/cpsprodpb/ab9e/live/ba2baae0-493e-11f1-861c-270dbba6d6ae.png",
      "categories": [
        "conflict"
      ],
      "relevanceScore": 8,
      "isAnalysis": false,
      "tags": []
    },
    {
      "id": "ans-cfd79546eb3a",
      "title": "Zelensky, 'Mosca ha violato tregua, agiremo di conseguenza'",
      "description": "'Ovvio che una guerra in corso non è il momento giusto per celebrazioni pubbliche'",
      "url": "https://www.ansa.it/sito/notizie/mondo/europa/2026/05/06/zelensky-mosca-ha-violato-tregua-agiremo-di-conseguenza_cc1c9f0b-5bee-439e-871f-0808293ed250.html",
      "source": "ANSA",
      "publishedAt": "2026-05-06T10:13:17Z",
      "image": "https://www.ansa.it/webimages/img_1129x635/2026/4/26/6cc8ded8d69ff72b07f26d0b40eff70c.jpg",
      "categories": [
        "conflict"
      ],
      "relevanceScore": 7,
      "isAnalysis": false,
      "tags": []
    },
    {
      "id": "npr-c11b7848c345",
      "title": "Skeletons in their clothing: Recovering bodies from the rubble in Gaza",
      "description": "It was one of the deadliest Israeli strikes of the Gaza war, devastating one extended family. A year and a half later, the survivors find their loved ones' remains.",
      "url": "https://www.npr.org/2026/05/06/nx-s1-5811930/gaza-recovering-bodies",
      "source": "NPR World",
      "publishedAt": "2026-05-06T09:00:00Z",
      "image": "https://npr.brightspotcdn.com/dims3/default/strip/false/crop/4032x3024+0+0/resize/4032x3024!/?url=http%3A%2F%2Fnpr-brightspot.s3.amazonaws.com%2F52%2F58%2Fdbfff96442b0a2172edea7029d4a%2F99542835-2def-4b48-8a73-848a63d4d6a9.jpg",
      "categories": [
        "conflict"
      ],
      "relevanceScore": 5,
      "isAnalysis": false,
      "tags": []
    },
    {
      "id": "rfe-ac5fb2d9cf7f",
      "title": "UAE Accuses Iran Of Hitting Oil Sector, World Leaders Condemn Dangerous Escalation",
      "description": "Several countries have condemned Iran and called an attack on oil facilities in the United Arab Emirates a dangerous escalation. Thick smoke was filmed pouring out from the Fujairah Oil Industry Zone that the UAE claimed was hit by an Iranian drone attack on May 4. This comes as both the US and Iran fired shots in the …",
      "url": "https://www.rferl.org/a/uae-accuses-iran-of-hitting-oil-sector-world-leaders-condemn-dangerous-escalation/33750468.html",
      "source": "RFE/RL",
      "publishedAt": "2026-05-05T13:59:36Z",
      "image": "https://gdb.rferl.org/7e6a2f66-de38-4ba2-6052-08de3c91433d_tv_w800_h450.jpg",
      "categories": [
        "conflict",
        "analysis"
      ],
      "relevanceScore": 13,
      "isAnalysis": true,
      "tags": []
    },
    {
      "id": "cs -cc90ddea1925",
      "title": "How Colombia became a top exporter of mercenaries",
      "description": "Every year Colombia retires thousands of battle-hardened veterans from its armed forces. Many end up enlisting in foreign conflicts.",
      "url": "https://www.csmonitor.com/World/Americas/2026/0505/How-Colombia-became-a-top-exporter-of-mercenaries?icid=rss",
      "source": "CS Monitor",
      "publishedAt": "2026-05-05T13:24:16Z",
      "image": "https://images.csmonitor.com/csm/2026/04/ZOCOLOMBIA_trio.jpg?alias=standard_900x600",
      "categories": [
        "conflict",
        "analysis"
      ],
      "relevanceScore": 9,
      "isAnalysis": true,
      "tags": []
    },
    {
      "id": "un -773008c4c373",
      "title": "Education or food? Funding shortfalls force Sudanese refugees in Egypt to ‘make very difficult decisions’",
      "description": "Civilians who have fled the war in Sudan and sought shelter in neighbouring Egypt could potentially face a new battle – the loss of critical services that ensure their survival, the UN refugee agency, UNHCR, has warned.&nbsp;",
      "url": "https://news.un.org/feed/view/en/story/2026/05/1167443",
      "source": "UN News",
      "publishedAt": "2026-05-05T12:00:00Z",
      "image": "https://global.unitednations.entermediadb.net/assets/mediadb/services/module/asset/downloads/preset/Collections/Production%20Library/30-04-2026-UNHCR-Egypt-Refugees-Reg.jpg/image560x340cropped.jpg",
      "categories": [
        "conflict"
      ],
      "relevanceScore": 9,
      "isAnalysis": false,
      "tags": []
    },
    {
      "id": "the-dfc761aa5bae",
      "title": "U.K. Targets Russian Army Recruitment Network and Drone Suppliers in Latest Sanctions Package",
      "description": "The new measures target what British officials condemned as a “barbaric” network that lures foreign nationals to Russia with the promise of work, only to force them into frontline combat in Ukraine or military production.",
      "url": "https://www.themoscowtimes.com/2026/05/05/uk-targets-russian-army-recruitment-network-and-drone-suppliers-in-latest-sanctions-package-a92683",
      "source": "The Moscow Times",
      "publishedAt": "2026-05-05T11:18:00Z",
      "image": "https://static.themoscowtimes.com/image/og/1f/92683__1f91d049d70457416b48e234e6d96689.jpg",
      "categories": [
        "conflict"
      ],
      "relevanceScore": 10,
      "isAnalysis": false,
      "tags": []
    }
  ]
}